xargproject/__init__.py
xargproject/command.py
xargproject/project.py
xkits_command/__init__.py
xkits_command/actuator.py
xkits_command/attribute.py
xkits_command/parser.py
xkits_command-0.5.3.dist-info/LICENSE
xkits_command-0.5.3.dist-info/METADATA
xkits_command-0.5.3.dist-info/WHEEL
xkits_command-0.5.3.dist-info/entry_points.txt
xkits_command-0.5.3.dist-info/top_level.txt
xkits_command-0.5.3.dist-info/zip-safe
xkits_command-0.5.3.dist-info/RECORD
