Metadata-Version: 2.1
Name: xkits-command
Version: 0.5.3
Summary: Command line module
Home-page: https://github.com/bondbox/xcommand/
Author: Mingzhe Zou
Author-email: zoumingzhe@outlook.com
License: GPLv2
Project-URL: Source Code, https://github.com/bondbox/xcommand/
Project-URL: Bug Tracker, https://github.com/bondbox/xcommand/issues
Project-URL: Documentation, https://github.com/bondbox/xcommand/
Keywords: command-line,argparse,argcomplete,shell,bash,terminal
Platform: any
Classifier: Programming Language :: Python
Classifier: Programming Language :: Python :: 3
Requires-Python: >=3.8
License-File: LICENSE
Requires-Dist: argcomplete >=3.2.1
Requires-Dist: xkits-logger >=0.2
